AUTHORS.md
CHANGES.md
LICENSE
MANIFEST.in
README.md
requirements.txt
setup.py
pytest_watch/__init__.py
pytest_watch/__main__.py
pytest_watch/command.py
pytest_watch/config.py
pytest_watch/constants.py
pytest_watch/helpers.py
pytest_watch/util.py
pytest_watch/watcher.py
pytest_watch.egg-info/PKG-INFO
pytest_watch.egg-info/SOURCES.txt
pytest_watch.egg-info/dependency_links.txt
pytest_watch.egg-info/entry_points.txt
pytest_watch.egg-info/requires.txt
pytest_watch.egg-info/top_level.txt