Metadata-Version: 1.0
Name: pytest-watch
Version: 4.1.0
Summary: Local continuous test runner with pytest and watchdog.
Home-page: http://github.com/joeyespo/pytest-watch
Author: Joe Esposito
Author-email: joe@joeyespo.com
License: MIT
Platform: any
